{"fecha_recepcion": "7/5/24", "fecha_entrega": "7/5/24", "nombre_responsable": "asda", "telefono_responsable": "sdasdasdasd", "area_responsable": "sadsad", "correo": "sadsadas", "descripcion_equipo": "Balanza digital", "otro_equipo": "", "falta_equipo": "asdasd", "modelo_equipo": "asdsad", "marca_equipo": "asdsad", "no_serie": "N/A", "no_inventario": "N/A", "descripcion_detallada": "asdasd", "estado_enciende": true, "estado_cable": false, "estado_componente": true, "estado_dano_botones": false, "estado_corrosion": false, "estado_dano_carcasa": false}